recsa/__init__.py
recsa/__main__.py
recsa/algorithms/__init__.py
recsa/algorithms/assembly_connectivity.py
recsa/algorithms/assembly_equality.py
recsa/algorithms/assembly_separation.py
recsa/algorithms/aux_edge_existence.py
recsa/algorithms/bindsite_equivalence.py
recsa/algorithms/bondset_sorting.py
recsa/algorithms/hashing.py
recsa/algorithms/isomorphic_assembly_search.py
recsa/algorithms/isomorphism/__init__.py
recsa/algorithms/isomorphism/isomorphism_check.py
recsa/algorithms/isomorphism/iteration.py
recsa/algorithms/isomorphism/pure_isomorphism_check.py
recsa/algorithms/isomorphism/rough_isomorphism_check.py
recsa/algorithms/isomorphism/rough_iteration.py
recsa/algorithms/isomorphism/tests/__init__.py
recsa/algorithms/isomorphism/tests/test_isomorphism_check.py
recsa/algorithms/isomorphism/tests/test_iteration.py
recsa/algorithms/isomorphism/tests/test_pure_isomorphism_check.py
recsa/algorithms/isomorphism/tests/test_rough_isomorphism_check.py
recsa/algorithms/isomorphism/tests/test_rough_iteration.py
recsa/algorithms/ligand_exchange/__init__.py
recsa/algorithms/ligand_exchange/inter.py
recsa/algorithms/ligand_exchange/intra.py
recsa/algorithms/ligand_exchange/tests/__init__.py
recsa/algorithms/ligand_exchange/tests/test_inter.py
recsa/algorithms/ligand_exchange/tests/test_intra.py
recsa/algorithms/reaction_comparison/__init__.py
recsa/algorithms/reaction_comparison/multiple_reaction_comparison.py
recsa/algorithms/reaction_comparison/reaction_comparison.py
recsa/algorithms/reaction_comparison/tests/__init__.py
recsa/algorithms/reaction_comparison/tests/test_multiple_reaction_comparison.py
recsa/algorithms/reaction_comparison/tests/test_reaction_comparison.py
recsa/algorithms/reaction_embedding.py
recsa/algorithms/subassembly.py
recsa/algorithms/tests/__init__.py
recsa/algorithms/tests/test_assembly_connectivity.py
recsa/algorithms/tests/test_assembly_equality.py
recsa/algorithms/tests/test_assembly_separation.py
recsa/algorithms/tests/test_aux_edge_existence.py
recsa-0.15.0.dist-info/LICENSE
recsa-0.15.0.dist-info/METADATA
recsa-0.15.0.dist-info/WHEEL
recsa-0.15.0.dist-info/entry_points.txt
recsa-0.15.0.dist-info/RECORD
